ideenergy/__init__.py
ideenergy/__main__.py
ideenergy/cli.py
ideenergy/client.py
ideenergy/parsers.py
ideenergy/types.py
ideenergy-2.0.0.dist-info/LICENSE
ideenergy-2.0.0.dist-info/METADATA
ideenergy-2.0.0.dist-info/WHEEL
ideenergy-2.0.0.dist-info/entry_points.txt
ideenergy-2.0.0.dist-info/top_level.txt
ideenergy-2.0.0.dist-info/RECORD
