Metadata-Version: 2.1
Name: ideenergy
Version: 2.0.0
Summary: Programmatic access to consumer energy consumption from https://www.i-de.es/ (Spanish energy distributor)
Author-email: Luis López <luis@cuarentaydos.com>
License: GNU GENERAL PUBLIC LICENSE
Project-URL: Homepage, https://github.com/ldotlopez/ideenergy
Project-URL: Issues, https://github.com/ldotlopez/ideenergy/issues
Project-URL: Repository, https://github.com/ldotlopez/ideenergy.git
Classifier: Programming Language :: Python :: 3
Classifier: License :: OSI Approved :: MIT License
Classifier: Operating System :: OS Independent
Requires-Python: >=3.11
License-File: LICENSE
Requires-Dist: aiohttp <4.0,>=3.8
Requires-Dist: importlib-metadata ; python_version >= "3.11"
